robot2cam_calibration-0.1.dist-info/entry_points.txt
robot2cam_calibration-0.1.dist-info/DESCRIPTION.rst
robot2cam_calibration-0.1.dist-info/top_level.txt
robot2cam_calibration-0.1.dist-info/METADATA
robot2cam_calibration-0.1.dist-info/metadata.json
robot2cam_calibration-0.1.dist-info/WHEEL
robot2cam_calibration-0.1.dist-info/RECORD
robot2cam_calibration/check_transformation.py
robot2cam_calibration/get_correspondences.py
robot2cam_calibration/camera.py
robot2cam_calibration/compute_transformations.py
robot2cam_calibration/__init__.py
robot2cam_calibration/track_grid.py
robot2cam_calibration/get_images.py
