Metadata-Version: 2.0
Name: robot2cam-calibration
Version: 0.1
Summary: A package to calibrate a robot arm to a camera
Home-page: https://github.com/IRIM-Technology-Transition-Lab/robot2camera-calibration
Author: Michael Sobrepera
Author-email: mjsobrep@live.com
License: The MIT License (MIT)
Requires-Dist: numpy
Requires-Dist: cv2
Requires-Dist: scipy
